rgd_3d/__init__.py
rgd_3d/apps.py
rgd_3d/serializers.py
rgd_3d/signals.py
rgd_3d/urls.py
rgd_3d/views.py
rgd_3d/admin/__init__.py
rgd_3d/admin/mesh.py
rgd_3d/admin/tiles.py
rgd_3d/management/commands/rgd_3d_demo.py
rgd_3d/migrations/0001_initial.py
rgd_3d/migrations/0002_alter_pointcloud_status.py
rgd_3d/migrations/0003_auto_20211116_1726.py
rgd_3d/migrations/0004_auto_20211116_1814.py
rgd_3d/migrations/0005_tiles3d_tiles3dmeta.py
rgd_3d/migrations/0006_alter_mesh3d_vtp_data.py
rgd_3d/migrations/__init__.py
rgd_3d/models/__init__.py
rgd_3d/models/mesh.py
rgd_3d/models/tiles.py
rgd_3d/rest/__init__.py
rgd_3d/rest/viewsets.py
rgd_3d/static/rgd_3d/vtkjs_viewer.js
rgd_3d/tasks/__init__.py
rgd_3d/tasks/etl.py
rgd_3d/tasks/jobs.py
rgd_3d/templates/admin/rgd_3d/mesh3d/change_form.html
rgd_3d/templates/rgd_3d/mesh3d_detail.html
rgd_3d/templates/rgd_3d/mesh3d_list.html
rgd_3d/templates/rgd_3d/tiles3d_detail.html
rgd_3d/templates/rgd_3d/_include/cesiumjs_viewer.html
rgd_3d/templates/rgd_3d/_include/vtkjs_viewer.html
tests/__init__.py
tests/conftest.py
tests/factories.py
tests/manage.py
tests/test_3d_tiles.py
tests/test_permissions.py
tests/test_point_cloud.py
tests/test_rest.py
tests/test_project/__init__.py
tests/test_project/settings.py
tests/test_project/urls.py
django_rgd_3d-0.3.11.dist-info/METADATA
django_rgd_3d-0.3.11.dist-info/WHEEL
django_rgd_3d-0.3.11.dist-info/top_level.txt
django_rgd_3d-0.3.11.dist-info/RECORD
